kaldigrpc_client/__init__.py
kaldigrpc_client/client.py
kaldigrpc_client/generated/__init__.py
kaldigrpc_client/generated/asr_pb2.py
kaldigrpc_client/generated/asr_pb2_grpc.py
kaldigrpc_client-1.0.1.dist-info/entry_points.txt
kaldigrpc_client-1.0.1.dist-info/WHEEL
kaldigrpc_client-1.0.1.dist-info/METADATA
kaldigrpc_client-1.0.1.dist-info/RECORD
