Metadata-Version: 2.1
Name: kaldigrpc-client
Version: 1.0.1
Summary: Python client for Kaldi GRPC server
Home-page: https://github.com/georgepar/kaldi-grpc-server
License: MIT
Keywords: speech recognition,kaldi,grpc,asr,deployment,streaming speech
Author: Giorgos Paraskevopoulos
Author-email: geopar@central.ntua.gr
Requires-Python: >=3.8,<4.0
Classifier: Development Status :: 3 - Alpha
Classifier: Environment :: Console
Classifier: Intended Audience :: Developers
Classifier: Intended Audience :: Science/Research
Classifier: License :: OSI Approved :: MIT License
Classifier: Operating System :: POSIX :: Linux
Classifier: Programming Language :: Python :: 3
Classifier: Programming Language :: Python :: 3.10
Classifier: Programming Language :: Python :: 3.8
Classifier: Programming Language :: Python :: 3.9
Classifier: Topic :: Multimedia :: Sound/Audio
Classifier: Topic :: Multimedia :: Sound/Audio :: Speech
Classifier: Topic :: Scientific/Engineering :: Artificial Intelligence
Requires-Dist: grpcio (>=1.51.1,<2.0.0)
Requires-Dist: grpcio-tools (>=1.51.1,<2.0.0)
Requires-Dist: pydub (>=0.25.1,<0.26.0)
Project-URL: Repository, https://github.com/georgepar/kaldi-grpc-server
